centara/__init__.py
centara-0.1.0.dist-info/LICENSE
centara-0.1.0.dist-info/METADATA
centara-0.1.0.dist-info/WHEEL
centara-0.1.0.dist-info/RECORD
