Metadata-Version: 2.1
Name: centara
Version: 0.1.0
Summary: Public Centara library
Author: grawfin
Author-email: grawfin@gmail.com
Requires-Python: >=3.10,<4.0
Classifier: Programming Language :: Python :: 3
Classifier: Programming Language :: Python :: 3.10
Classifier: Programming Language :: Python :: 3.11
Classifier: Programming Language :: Python :: 3.12
Classifier: Programming Language :: Python :: 3.13
